CHANGELOG.txt
LICENSE.txt
MANIFEST.in
README.txt
setup.py
pyshooter2d/__init__.py
pyshooter2d.egg-info/PKG-INFO
pyshooter2d.egg-info/SOURCES.txt
pyshooter2d.egg-info/dependency_links.txt
pyshooter2d.egg-info/requires.txt
pyshooter2d.egg-info/top_level.txt