Metadata-Version: 2.1
Name: pyshooter2d
Version: 0.0.3
Summary: A package for easier and faster development of 2d shooters with pygame
Home-page: 
Author: Freddy Frolov
Author-email: freddyfrolov383@gmail.com
License: MIT
Keywords: shooter engine
Classifier: Development Status :: 5 - Production/Stable
Classifier: Intended Audience :: Developers
Classifier: Operating System :: Microsoft :: Windows :: Windows 10
Classifier: License :: OSI Approved :: MIT License
Classifier: Programming Language :: Python :: 3
License-File: LICENSE.txt
